climeon/__init__.py
climeon/api.py
climeon/data_finder.py
climeon/identifiers.py
climeon/plotting.py
climeon/logreader/__init__.py
climeon/logreader/synonyms.py
climeon-2.2.0.dist-info/METADATA
climeon-2.2.0.dist-info/WHEEL
climeon-2.2.0.dist-info/top_level.txt
climeon-2.2.0.dist-info/RECORD
