Metadata-Version: 2.4
Name: climeon
Version: 2.2.0
Summary: Climeon API client
Author: Emil Hjelm
Author-email: emil.hjelm@climeon.com
License: MIT
Keywords: climeon,REST,API
Classifier: Development Status :: 3 - Alpha
Classifier: Intended Audience :: Developers
Classifier: Topic :: Software Development :: Libraries :: Python Modules
Classifier: License :: OSI Approved :: MIT License
Classifier: Programming Language :: Python
Classifier: Operating System :: OS Independent
Requires-Python: >=3.9
Requires-Dist: plotly
Requires-Dist: msal
Requires-Dist: pandas
Requires-Dist: requests
Requires-Dist: dateparser
Requires-Dist: tzlocal
Dynamic: author
Dynamic: author-email
Dynamic: classifier
Dynamic: description
Dynamic: keywords
Dynamic: license
Dynamic: requires-dist
Dynamic: requires-python
Dynamic: summary
